.DS_Store
highlight_text/__init__.py
highlight_text/htext.py
highlight_text-0.2.dist-info/LICENSE.txt
highlight_text-0.2.dist-info/METADATA
highlight_text-0.2.dist-info/WHEEL
highlight_text-0.2.dist-info/top_level.txt
highlight_text-0.2.dist-info/RECORD
