Metadata-Version: 2.1
Name: highlight-text
Version: 0.2
Summary: matplotlib functions to plot text with color highlighted substrings
Home-page: https://github.com/znstrider/highlight_text
Author: znstrider
Author-email: mindfulstrider@gmail.com
License: UNKNOWN
Platform: UNKNOWN
Classifier: Programming Language :: Python :: 3
Classifier: License :: OSI Approved :: MIT License
Classifier: Operating System :: OS Independent
Classifier: Framework :: Matplotlib
Classifier: Topic :: Scientific/Engineering :: Visualization
Requires-Python: >=3.6
